setup.py
py_find_injection/__init__.py
py_find_injection.egg-info/PKG-INFO
py_find_injection.egg-info/SOURCES.txt
py_find_injection.egg-info/dependency_links.txt
py_find_injection.egg-info/entry_points.txt
py_find_injection.egg-info/top_level.txt