Metadata-Version: 1.1
Name: py-find-injection
Version: 0.1.1
Summary: simple python ast consumer which searches for common SQL injection attacks
Home-page: https://github.com/uber/py-find-injection
Author: James Brown
Author-email: jbrown@uber.com
License: MIT (Expat)
Platform: UNKNOWN
Classifier: Programming Language :: Python
Classifier: Operating System :: OS Independent
Classifier: Topic :: Security
Classifier: Topic :: Security
Classifier: Intended Audience :: Developers
Classifier: Development Status :: 3 - Alpha
Classifier: Programming Language :: Python :: 2.7
Classifier: License :: OSI Approved :: MIT License
